{"version":1,"resource":"file:///c%3A/Users/bc/.continue/config.yaml","entries":[{"id":"2nZl.yaml","timestamp":1779238761666},{"id":"6oGs.yaml","timestamp":1779238858641},{"id":"GsQZ.yaml","timestamp":1779239114739},{"id":"IJDZ.yaml","source":"undoRedo.source","timestamp":1779239117874},{"id":"us2I.yaml","timestamp":1779239129690},{"id":"SSDs.yaml","timestamp":1779239384701},{"id":"SHLK.yaml","source":"undoRedo.source","timestamp":1779239398694},{"id":"0edC.yaml","source":"undoRedo.source","timestamp":1779239454591},{"id":"gTeR.yaml","timestamp":1779239454947},{"id":"H8Qt.yaml","source":"undoRedo.source","timestamp":1779239581015},{"id":"JDJF.yaml","source":"undoRedo.source","timestamp":1779239606173},{"id":"g0Q6.yaml","timestamp":1779239607139},{"id":"B8Rl.yaml","timestamp":1779239729789},{"id":"FYT7.yaml","source":"undoRedo.source","timestamp":1779239731974},{"id":"DGrx.yaml","timestamp":1779240381473},{"id":"4lAE.yaml","source":"undoRedo.source","timestamp":1779240384434},{"id":"eilB.yaml","timestamp":1779240583457},{"id":"2OIG.yaml","source":"undoRedo.source","timestamp":1779240621079},{"id":"JdKr.yaml","timestamp":1779240626989},{"id":"dQUc.yaml","timestamp":1779240659309},{"id":"BaCs.yaml","timestamp":1779240724828},{"id":"YsTn.yaml","source":"undoRedo.source","timestamp":1779240782331},{"id":"3LCc.yaml","source":"undoRedo.source","timestamp":1779240913155},{"id":"EQ76.yaml","timestamp":1779240914675},{"id":"4Iha.yaml","timestamp":1779240929146},{"id":"RsnW.yaml","source":"undoRedo.source","timestamp":1779240939980},{"id":"KOMu.yaml","timestamp":1779241111536},{"id":"JazB.yaml","timestamp":1779241179956},{"id":"ww2E.yaml","timestamp":1779241301738},{"id":"TWUh.yaml","source":"undoRedo.source","timestamp":1779241362909},{"id":"XOXP.yaml","timestamp":1779241379903},{"id":"kAWh.yaml","timestamp":1779241396618},{"id":"D7uN.yaml","source":"undoRedo.source","timestamp":1779241412223},{"id":"5B1G.yaml","timestamp":1779241459989},{"id":"WWVJ.yaml","source":"undoRedo.source","timestamp":1779241461348}]}